README.md
setup.py
ksmyvoteinfo/__init__.py
ksmyvoteinfo/client.py
ksmyvoteinfo/counties.py
ksmyvoteinfo.egg-info/PKG-INFO
ksmyvoteinfo.egg-info/SOURCES.txt
ksmyvoteinfo.egg-info/dependency_links.txt
ksmyvoteinfo.egg-info/not-zip-safe
ksmyvoteinfo.egg-info/requires.txt
ksmyvoteinfo.egg-info/top_level.txt