Metadata-Version: 1.0
Name: ksmyvoteinfo
Version: 1.5
Summary: Query the KS SOS site for voter registration
Home-page: http://github.com/BlueprintKansas/ksmyvoteinfo-py
Author: Peter Karman
Author-email: peter@peknet.com
License: MIT
Platform: UNKNOWN
